Workbook

Sheet Read me
A1: Charitable Donation Log — 2026
A2: How to use this workbook
A3: 1. Log each gift on the Gifts sheet: date, organization, what it was, the type (Cash, Non-cash, or Securities), and the amount or fair market value. For securities add the cost basis and whether you held them more than a year.
A4: 2. The sheet calculates the deductible amount and flags what documentation each gift needs.
A5: 3. The Summary sheet totals by type and lists the flags. Send the workbook to Grott Luker & Co. in January with your receipt letters.
A7: Documentation rules
A8: • Any single gift of $250 or more needs a contemporaneous written acknowledgment from the charity before you file. Mark the Receipt column Y once you have it.
A9: • Non-cash gifts over $500 in total require Form 8283 with the return.
A10: • Any non-cash item or group of similar items over $5,000 needs a qualified appraisal (publicly traded securities excepted).
A11: • Appreciated securities held more than a year are deductible at fair market value and the capital gain is never taxed. Held a year or less, the deduction is limited to cost basis.
A12: • Qualified charitable distributions from an IRA (70½+) are excluded from income instead of deducted; log them with a note so your CPA sees them.
A14: Yellow cells are yours to fill in. White cells calculate themselves.
A15: This workbook organizes gifts and flags documentation rules; it does not determine deductibility, which depends on the donee, AGI limits, and your facts. Review with Grott Luker & Co. before filing.

Sheet Gifts
A1: Gifts — 2026
A2: One row per gift. Deductible amount and flags calculate from the type, amount, basis, and holding period.
A3: Grott Luker & Co. · Client Decision Support Toolkit · platform by BlueLine Advisors
A4: Yellow cells are yours to fill in. White cells calculate themselves — leave them alone.
A5: Date | B5: Organization | C5: Description | D5: Type | E5: Amount / FMV | F5: Cost basis (securities) | G5: Held > 1 yr (Y/N) | H5: Receipt letter (Y/N) | I5: Deductible | J5: Flags
I6: =IF(OR(D6="",E6=""),"",IF(D6="Securities",IF(G6="N",MIN(E6,IF(F6="",E6,F6)),E6),E6)) | J6: =IF(E6="","",TRIM(IF(AND(E6>=250,H6<>"Y"),"Receipt letter needed. ","")&IF(AND(D6<>"Cash",E6>5000),"Appraisal likely (>$5,000 non-cash). ","")&IF(AND(D6="Securities",G6="N"),"Short-term: limited to basis. ","")))
I7: =IF(OR(D7="",E7=""),"",IF(D7="Securities",IF(G7="N",MIN(E7,IF(F7="",E7,F7)),E7),E7)) | J7: =IF(E7="","",TRIM(IF(AND(E7>=250,H7<>"Y"),"Receipt letter needed. ","")&IF(AND(D7<>"Cash",E7>5000),"Appraisal likely (>$5,000 non-cash). ","")&IF(AND(D7="Securities",G7="N"),"Short-term: limited to basis. ","")))
I8: =IF(OR(D8="",E8=""),"",IF(D8="Securities",IF(G8="N",MIN(E8,IF(F8="",E8,F8)),E8),E8)) | J8: =IF(E8="","",TRIM(IF(AND(E8>=250,H8<>"Y"),"Receipt letter needed. ","")&IF(AND(D8<>"Cash",E8>5000),"Appraisal likely (>$5,000 non-cash). ","")&IF(AND(D8="Securities",G8="N"),"Short-term: limited to basis. ","")))
I9: =IF(OR(D9="",E9=""),"",IF(D9="Securities",IF(G9="N",MIN(E9,IF(F9="",E9,F9)),E9),E9)) | J9: =IF(E9="","",TRIM(IF(AND(E9>=250,H9<>"Y"),"Receipt letter needed. ","")&IF(AND(D9<>"Cash",E9>5000),"Appraisal likely (>$5,000 non-cash). ","")&IF(AND(D9="Securities",G9="N"),"Short-term: limited to basis. ","")))
I10: =IF(OR(D10="",E10=""),"",IF(D10="Securities",IF(G10="N",MIN(E10,IF(F10="",E10,F10)),E10),E10)) | J10: =IF(E10="","",TRIM(IF(AND(E10>=250,H10<>"Y"),"Receipt letter needed. ","")&IF(AND(D10<>"Cash",E10>5000),"Appraisal likely (>$5,000 non-cash). ","")&IF(AND(D10="Securities",G10="N"),"Short-term: limited to basis. ","")))
I11: =IF(OR(D11="",E11=""),"",IF(D11="Securities",IF(G11="N",MIN(E11,IF(F11="",E11,F11)),E11),E11)) | J11: =IF(E11="","",TRIM(IF(AND(E11>=250,H11<>"Y"),"Receipt letter needed. ","")&IF(AND(D11<>"Cash",E11>5000),"Appraisal likely (>$5,000 non-cash). ","")&IF(AND(D11="Securities",G11="N"),"Short-term: limited to basis. ","")))
I12: =IF(OR(D12="",E12=""),"",IF(D12="Securities",IF(G12="N",MIN(E12,IF(F12="",E12,F12)),E12),E12)) | J12: =IF(E12="","",TRIM(IF(AND(E12>=250,H12<>"Y"),"Receipt letter needed. ","")&IF(AND(D12<>"Cash",E12>5000),"Appraisal likely (>$5,000 non-cash). ","")&IF(AND(D12="Securities",G12="N"),"Short-term: limited to basis. ","")))
I13: =IF(OR(D13="",E13=""),"",IF(D13="Securities",IF(G13="N",MIN(E13,IF(F13="",E13,F13)),E13),E13)) | J13: =IF(E13="","",TRIM(IF(AND(E13>=250,H13<>"Y"),"Receipt letter needed. ","")&IF(AND(D13<>"Cash",E13>5000),"Appraisal likely (>$5,000 non-cash). ","")&IF(AND(D13="Securities",G13="N"),"Short-term: limited to basis. ","")))
I14: =IF(OR(D14="",E14=""),"",IF(D14="Securities",IF(G14="N",MIN(E14,IF(F14="",E14,F14)),E14),E14)) | J14: =IF(E14="","",TRIM(IF(AND(E14>=250,H14<>"Y"),"Receipt letter needed. ","")&IF(AND(D14<>"Cash",E14>5000),"Appraisal likely (>$5,000 non-cash). ","")&IF(AND(D14="Securities",G14="N"),"Short-term: limited to basis. ","")))
I15: =IF(OR(D15="",E15=""),"",IF(D15="Securities",IF(G15="N",MIN(E15,IF(F15="",E15,F15)),E15),E15)) | J15: =IF(E15="","",TRIM(IF(AND(E15>=250,H15<>"Y"),"Receipt letter needed. ","")&IF(AND(D15<>"Cash",E15>5000),"Appraisal likely (>$5,000 non-cash). ","")&IF(AND(D15="Securities",G15="N"),"Short-term: limited to basis. ","")))
I16: =IF(OR(D16="",E16=""),"",IF(D16="Securities",IF(G16="N",MIN(E16,IF(F16="",E16,F16)),E16),E16)) | J16: =IF(E16="","",TRIM(IF(AND(E16>=250,H16<>"Y"),"Receipt letter needed. ","")&IF(AND(D16<>"Cash",E16>5000),"Appraisal likely (>$5,000 non-cash). ","")&IF(AND(D16="Securities",G16="N"),"Short-term: limited to basis. ","")))
I17: =IF(OR(D17="",E17=""),"",IF(D17="Securities",IF(G17="N",MIN(E17,IF(F17="",E17,F17)),E17),E17)) | J17: =IF(E17="","",TRIM(IF(AND(E17>=250,H17<>"Y"),"Receipt letter needed. ","")&IF(AND(D17<>"Cash",E17>5000),"Appraisal likely (>$5,000 non-cash). ","")&IF(AND(D17="Securities",G17="N"),"Short-term: limited to basis. ","")))
... I205: =IF(OR(D205="",E205=""),"",IF(D205="Securities",IF(G205="N",MIN(E205,IF(F205="",E205,F205)),E205),E205)) | J205: =IF(E205="","",TRIM(IF(AND(E205>=250,H205<>"Y"),"Receipt letter needed. ","")&IF(AND(D205<>"Cash",E205>5000),"Appraisal likely (>$5,000 non-cash). ","")&IF(AND(D205="Securities",G205="N"),"Short-term: limited to basis. ","")))
D207: Totals | E207: =SUM(E6:E205) | I207: =SUM(I6:I205)

Sheet Summary
A1: Summary — 2026
A2: Totals by gift type and the documentation checklist.
A3: Grott Luker & Co. · Client Decision Support Toolkit · platform by BlueLine Advisors
A5: Gift type | B5: Gifts | C5: Deductible | D5: Count
A6: Cash | B6: =SUMIFS(Gifts!$E$6:$E$205,Gifts!$D$6:$D$205,"Cash") | C6: =SUMIFS(Gifts!$I$6:$I$205,Gifts!$D$6:$D$205,"Cash") | D6: =COUNTIFS(Gifts!$D$6:$D$205,"Cash",Gifts!$E$6:$E$205,">0")
A7: Non-cash | B7: =SUMIFS(Gifts!$E$6:$E$205,Gifts!$D$6:$D$205,"Non-cash") | C7: =SUMIFS(Gifts!$I$6:$I$205,Gifts!$D$6:$D$205,"Non-cash") | D7: =COUNTIFS(Gifts!$D$6:$D$205,"Non-cash",Gifts!$E$6:$E$205,">0")
A8: Securities | B8: =SUMIFS(Gifts!$E$6:$E$205,Gifts!$D$6:$D$205,"Securities") | C8: =SUMIFS(Gifts!$I$6:$I$205,Gifts!$D$6:$D$205,"Securities") | D8: =COUNTIFS(Gifts!$D$6:$D$205,"Securities",Gifts!$E$6:$E$205,">0")
A9: All gifts | B9: =SUM(B6:B8) | C9: =SUM(C6:C8) | D9: =SUM(D6:D8)
A11: Documentation checklist | C11: Result
A12: Gifts of $250+ still missing a receipt letter | C12: =COUNTIFS(Gifts!$E$6:$E$205,">=250",Gifts!$H$6:$H$205,"<>Y",Gifts!$E$6:$E$205,">0")
A13: Non-cash total (Form 8283 required over $500) | C13: =SUMIFS(Gifts!$E$6:$E$205,Gifts!$D$6:$D$205,"<>Cash")
A14: Form 8283 needed? | C14: =IF(C13>500,"Yes","No")
A15: Non-cash items over $5,000 (appraisal) | C15: =COUNTIFS(Gifts!$D$6:$D$205,"<>Cash",Gifts!$E$6:$E$205,">5000")
A16: Capital gain avoided on long-term securities | C16: =SUMPRODUCT((Gifts!$D$6:$D$205="Securities")*(Gifts!$G$6:$G$205="Y")*(Gifts!$E$6:$E$205-Gifts!$F$6:$F$205))
A18: Thresholds: IRC §170(f)(8) acknowledgment at $250; Form 8283 above $500 of non-cash gifts; qualified appraisal above $5,000 per item or group.
